openobserve/__init__.py
openobserve/generate.py
openobserve/global_exception_logger.py
openobserve-1.0.2.dist-info/LICENSE
openobserve-1.0.2.dist-info/METADATA
openobserve-1.0.2.dist-info/WHEEL
openobserve-1.0.2.dist-info/top_level.txt
openobserve-1.0.2.dist-info/RECORD
