Metadata-Version: 2.1
Name: openobserve
Version: 1.0.2
Summary: OpenObserve library
Author: Krzysztof Żyłka
Author-email: krzysztofzylka@yahoo.com
Classifier: Programming Language :: Python :: 3
Classifier: License :: OSI Approved :: MIT License
Classifier: Operating System :: OS Independent
License-File: LICENSE
Requires-Dist: requests
Requires-Dist: jsonex
